simplejson-stubs/METADATA.toml
simplejson-stubs/__init__.pyi
simplejson-stubs/decoder.pyi
simplejson-stubs/encoder.pyi
simplejson-stubs/errors.pyi
simplejson-stubs/py.typed
simplejson-stubs/raw_json.pyi
simplejson-stubs/scanner.pyi
types_simplejson-3.20.0.20250326.dist-info/licenses/LICENSE
types_simplejson-3.20.0.20250326.dist-info/METADATA
types_simplejson-3.20.0.20250326.dist-info/WHEEL
types_simplejson-3.20.0.20250326.dist-info/top_level.txt
types_simplejson-3.20.0.20250326.dist-info/RECORD
